artefacts_utils_rosbag_gpl/__init__.py
artefacts_utils_rosbag_gpl/ros2bag2video.py
artefacts_utils_rosbag_gpl/version.py
artefacts_utils_rosbag_gpl-0.1.6.dist-info/LICENSE
artefacts_utils_rosbag_gpl-0.1.6.dist-info/METADATA
artefacts_utils_rosbag_gpl-0.1.6.dist-info/WHEEL
artefacts_utils_rosbag_gpl-0.1.6.dist-info/top_level.txt
artefacts_utils_rosbag_gpl-0.1.6.dist-info/RECORD
