Metadata-Version: 2.1
Name: artefacts-utils-rosbag-gpl
Version: 0.1.6
Author-email: TN <tomo@artefacts.com>
Project-URL: Homepage, https://github.com/art-e-fact/artefacts_utils_rosbag_gpl
Project-URL: Bug Tracker, https://github.com/art-e-fact/artefacts_utils_rosbag_gpl/issues
Classifier: Programming Language :: Python :: 3
Classifier: License :: OSI Approved :: Apache Software License
Classifier: Operating System :: OS Independent
Requires-Python: >=3.10
License-File: LICENSE
Requires-Dist: opencv-python
Requires-Dist: numpy<2,>=1.26.0
Provides-Extra: dev
Requires-Dist: build; extra == "dev"
Requires-Dist: pyre-check; extra == "dev"
Requires-Dist: pytest; extra == "dev"
Requires-Dist: pytest-cov; extra == "dev"
Requires-Dist: pytest-env; extra == "dev"
Requires-Dist: pytest-mock; extra == "dev"
Requires-Dist: ruff; extra == "dev"
Requires-Dist: setuptools-scm; extra == "dev"
Requires-Dist: twine; extra == "dev"
